bagpype/__init__.py
bagpype/models.py
bagpype/pipeline.py
bagpype/visualization.py
bagpype-0.1.2.dist-info/WHEEL
bagpype-0.1.2.dist-info/METADATA
bagpype-0.1.2.dist-info/RECORD
