Metadata-Version: 2.3
Name: bagpype
Version: 0.1.2
Summary: A python library for pipeline diagram visualization
Keywords: pipeline,visualization,computer architecture
License: MIT
Requires-Dist: matplotlib>=3.7.0
Requires-Dist: seaborn>=0.12.0
Requires-Dist: pytest>=7.0.0 ; extra == 'dev'
Requires-Python: >=3.10
Project-URL: Homepage, https://github.com/iansseijelly/bagpype
Provides-Extra: dev
